emodbus/__init__.py
emodbus/constants.py
emodbus/emodbus.py
emodbus/modbustypes.py
emodbus/test.py
emodbus-0.0.5.dist-info/LICENCE
emodbus-0.0.5.dist-info/METADATA
emodbus-0.0.5.dist-info/WHEEL
emodbus-0.0.5.dist-info/top_level.txt
emodbus-0.0.5.dist-info/RECORD
